qsilver/LICENSE.txt
qsilver/README.md
qsilver/__init__.py
qsilver/api.py
qsilver/async_socket.py
qsilver/base_handler.py
qsilver/base_scheduler.py
qsilver/coro_proxy.py
qsilver/handlers.py
qsilver/scheduler.py
qsilver/tcp_server.py
qsilver/yield_proxy.py
qsilver-0.2.dist-info/METADATA
qsilver-0.2.dist-info/WHEEL
qsilver-0.2.dist-info/top_level.txt
qsilver-0.2.dist-info/RECORD
