Metadata-Version: 2.1
Name: qsilver
Version: 0.2
Summary: UNKNOWN
Home-page: https://github.com/sesevasa64/qsilver
Author: Vsevolod Vlasov
Author-email: sesevasa64@gmail.com
License: MIT
Keywords: async,concurrent
Platform: UNKNOWN
